python3_smpplib-1.0.17.dist-info/DESCRIPTION.rst
python3_smpplib-1.0.17.dist-info/METADATA
python3_smpplib-1.0.17.dist-info/RECORD
python3_smpplib-1.0.17.dist-info/WHEEL
python3_smpplib-1.0.17.dist-info/metadata.json
python3_smpplib-1.0.17.dist-info/top_level.txt
python3_smpplib-1.0.17.dist-info/zip-safe
smpplib/__init__.py
smpplib/client.py
smpplib/command.py
smpplib/command_codes.py
smpplib/consts.py
smpplib/exceptions.py
smpplib/gsm.py
smpplib/pdu.py
smpplib/ptypes.py
smpplib/server.py
smpplib/smpp.py
